daskernetes/__init__.py
daskernetes/config.py
daskernetes/core.py
daskernetes/objects.py
daskernetes-0.1.3.dist-info/DESCRIPTION.rst
daskernetes-0.1.3.dist-info/METADATA
daskernetes-0.1.3.dist-info/RECORD
daskernetes-0.1.3.dist-info/WHEEL
daskernetes-0.1.3.dist-info/metadata.json
daskernetes-0.1.3.dist-info/top_level.txt
