Metadata-Version: 2.0
Name: daskernetes
Version: 0.1.3
Summary: Native Kubernetes integration for Dask
Home-page: https://github.com/dask/daskernetes
Author: UNKNOWN
Author-email: UNKNOWN
License: BSD
Keywords: dask,kubernetes,distributed
Platform: UNKNOWN
Requires-Dist: dask[distributed]
Requires-Dist: kubernetes (==4)
